README.md
setup.py
gui_menu.egg-info/PKG-INFO
gui_menu.egg-info/SOURCES.txt
gui_menu.egg-info/dependency_links.txt
gui_menu.egg-info/requires.txt
gui_menu.egg-info/top_level.txt
menu/__init__.py
menu/__main__.py
menu/keyboard/__init__.py
menu/keyboard/__main__.py
menu/keyboard/_canonical_names.py
menu/keyboard/_darwinkeyboard.py
menu/keyboard/_darwinmouse.py
menu/keyboard/_generic.py
menu/keyboard/_keyboard_event.py
menu/keyboard/_keyboard_tests.py
menu/keyboard/_mouse_event.py
menu/keyboard/_mouse_tests.py
menu/keyboard/_nixcommon.py
menu/keyboard/_nixkeyboard.py
menu/keyboard/_nixmouse.py
menu/keyboard/_winkeyboard.py
menu/keyboard/_winmouse.py
menu/keyboard/mouse.py