Metadata-Version: 2.1
Name: gui-menu
Version: 2.0.1
Summary: Create easy-to-use gui menus for your projects.
Home-page: UNKNOWN
Author: Seth Peace
Author-email: sethevanpeace@gmail.com
License: MIT
Platform: UNKNOWN
Classifier: License :: OSI Approved :: MIT License
Classifier: Development Status :: 4 - Beta
Classifier: Environment :: Console
Classifier: Intended Audience :: Developers
Classifier: Topic :: Software Development :: User Interfaces
Requires-Python: ==3.7.0
